phort/__init__.py
phort/__main__.py
phort/phort.py
phort-0.1.1.dist-info/METADATA
phort-0.1.1.dist-info/WHEEL
phort-0.1.1.dist-info/entry_points.txt
phort-0.1.1.dist-info/top_level.txt
phort-0.1.1.dist-info/RECORD
